[
    {
        "pose": {
            "mode": 0,
            "q_w": -0.6229361295700073,
            "q_x": 0.0030469729099422693,
            "q_y": -0.05463699251413345,
            "q_z": 0.7803563475608826,
            "speed": 0.800000011920929,
            "x": 1.401647686958313,
            "y": -0.5957909226417542,
            "z": 0.0776044949889183
        },
        "qrText": "Qr 2 also detected",
        "taskIndex": 0
    },
    {
        "pose": {
            "mode": 0,
            "q_w": 0.9192807078361511,
            "q_x": -0.007094718981534243,
            "q_y": 0.041666992008686066,
            "q_z": 0.3913266360759735,
            "speed": 0.800000011920929,
            "x": 4.052014350891113,
            "y": 1.1063897609710693,
            "z": -0.04033813625574112
        },
        "qrText": "https://www.qrcode-monkey.com",
        "taskIndex": 1
    },
    {
        "pose": {
            "mode": 0,
            "q_w": -0.12339232116937637,
            "q_x": -0.003395646344870329,
            "q_y": 0.03685055300593376,
            "q_z": -0.9916676878929138,
            "speed": 0.800000011920929,
            "x": 2.5107760429382324,
            "y": 2.325101137161255,
            "z": 0.10480800271034241
        },
        "qrText": "Lada it worked",
        "taskIndex": 2
    }
]
